crap/__init__.py
crap/cli.py
crap/crap_manager.py
crap/file_analyzer.py
crap/module_checker.py
crap/package_management.py
crap/package_usage_counter.py
crap/subprocesses.py
crap/virtual_env_checker.py
crap/data/__init__.py
crap/data/default_important_packages.txt
crap/data/important_packages.txt
crap/data/req.txt
just_crap-1.0.2.dist-info/LICENSE
just_crap-1.0.2.dist-info/METADATA
just_crap-1.0.2.dist-info/WHEEL
just_crap-1.0.2.dist-info/entry_points.txt
just_crap-1.0.2.dist-info/top_level.txt
just_crap-1.0.2.dist-info/RECORD
