Metadata-Version: 2.1
Name: just-crap
Version: 1.0.2
Summary: UNKNOWN
Home-page: UNKNOWN
Author: Valdon Vitija
Author-email: valdonvitijaa@gmail.com
License: MIT
Platform: UNKNOWN
License-File: LICENSE
Requires-Dist: pytest
Requires-Dist: ruff
Requires-Dist: tqdm
Requires-Dist: typer[all] ==0.9.0
